README.md
setup.py
capy/__init__.py
capy/bds.py
capy/capy.py
capy/cmd.py
capy/conf.py
capy/device.py
capy/device_os.py
capy/error.py
capy/test.py
capy/util.py
capy.egg-info/PKG-INFO
capy.egg-info/SOURCES.txt
capy.egg-info/dependency_links.txt
capy.egg-info/entry_points.txt
capy.egg-info/requires.txt
capy.egg-info/top_level.txt