Metadata-Version: 1.1
Name: capy
Version: 1.1.14
Summary: CAPY is a helper for running calabash tests on iOS and Android
Home-page: https://github.com/FrantisekGazo/capy/
Author: František Gažo
Author-email: frantisek.gazo@inloop.eu
License: MIT License
Platform: MacOS
Classifier: Programming Language :: Python :: 2.7
Classifier: Development Status :: 1 - Planning
Classifier: Operating System :: MacOS
Classifier: License :: OSI Approved :: MIT License
Classifier: Natural Language :: English
Classifier: Topic :: Utilities
